AwaitMyanimelist/__init__.py
AwaitMyanimelist/anime.py
AwaitMyanimelist/main.py
AwaitMyanimelist/malUser.py
AwaitMyanimelist/mal_client.py
AwaitMyanimelist/manga.py
AwaitMyanimelist-0.0.1.dist-info/METADATA
AwaitMyanimelist-0.0.1.dist-info/WHEEL
AwaitMyanimelist-0.0.1.dist-info/top_level.txt
AwaitMyanimelist-0.0.1.dist-info/RECORD
