Metadata-Version: 2.1
Name: AwaitMyanimelist
Version: 0.0.1
Summary: a async package for myanimelist api v2
Home-page: UNKNOWN
Author: resetxd
License: UNKNOWN
Keywords: python,async,mal,myanimelist,api,api wrapper,discord
Platform: UNKNOWN
Classifier: Development Status :: 1 - Planning
Classifier: Intended Audience :: Developers
Classifier: Programming Language :: Python :: 3
Classifier: Operating System :: Unix
Classifier: Operating System :: MacOS :: MacOS X
Classifier: Operating System :: Microsoft :: Windows
Requires-Dist: aiohttp
